{
  "paragraphs": [
    {
      "text": "ls -lah",
      "user": "anonymous",
      "dateUpdated": "2018-12-12 18:08:59.647",
      "config": {
        "colWidth": 12.0,
        "fontSize": 9.0,
        "enabled": true,
        "results": {},
        "editorSetting": {
          "language": "sh",
          "editOnDblClick": false,
          "completionSupport": false
        },
        "editorMode": "ace/mode/sh"
      },
      "settings": {
        "params": {},
        "forms": {}
      },
      "results": {
        "code": "SUCCESS",
        "msg": [
          {
            "type": "TEXT",
            "data": "total 4.0K\ndrwxr-xr-x  4 zeppelin zeppelin   62 Dec 12 17:50 .\ndrwxr-xr-x 50 hadoop   hadoop   4.0K Dec 12 17:43 ..\ndrwxr-xr-x  3 zeppelin zeppelin   35 Dec 11 21:53 local-repo\ndrwxr-xr-x  7 zeppelin zeppelin  103 Dec 12 18:03 notebook\n-rw-r--r--  1 zeppelin zeppelin    0 Dec 12 17:09 .scala_history\n"
          }
        ]
      },
      "apps": [],
      "jobName": "paragraph_1544637797693_-603893816",
      "id": "20181212-180317_1492971428",
      "dateCreated": "2018-12-12 18:03:17.693",
      "dateStarted": "2018-12-12 18:08:59.663",
      "dateFinished": "2018-12-12 18:09:02.119",
      "status": "FINISHED",
      "progressUpdateIntervalMs": 500
    },
    {
      "text": "pwd",
      "user": "anonymous",
      "dateUpdated": "2018-12-12 18:21:24.804",
      "config": {
        "colWidth": 12.0,
        "fontSize": 9.0,
        "enabled": true,
        "results": {},
        "editorSetting": {}
      },
      "settings": {
        "params": {},
        "forms": {}
      },
      "results": {
        "code": "SUCCESS",
        "msg": [
          {
            "type": "TEXT",
            "data": "/var/lib/zeppelin\n"
          }
        ]
      },
      "apps": [],
      "jobName": "paragraph_1544638139647_1897189662",
      "id": "20181212-180859_1980789742",
      "dateCreated": "2018-12-12 18:08:59.647",
      "dateStarted": "2018-12-12 18:21:24.847",
      "dateFinished": "2018-12-12 18:21:24.874",
      "status": "FINISHED",
      "progressUpdateIntervalMs": 500
    },
    {
      "text": "ls",
      "user": "anonymous",
      "dateUpdated": "2018-12-12 18:24:59.766",
      "config": {
        "colWidth": 12.0,
        "fontSize": 9.0,
        "enabled": true,
        "results": {},
        "editorSetting": {
          "language": "sh",
          "editOnDblClick": false,
          "completionSupport": false
        },
        "editorMode": "ace/mode/sh"
      },
      "settings": {
        "params": {},
        "forms": {}
      },
      "results": {
        "code": "SUCCESS",
        "msg": [
          {
            "type": "TEXT",
            "data": "local-repo\nnotebook\n"
          }
        ]
      },
      "apps": [],
      "jobName": "paragraph_1544638884804_-142647081",
      "id": "20181212-182124_148403499",
      "dateCreated": "2018-12-12 18:21:24.804",
      "dateStarted": "2018-12-12 18:24:59.797",
      "dateFinished": "2018-12-12 18:24:59.854",
      "status": "FINISHED",
      "progressUpdateIntervalMs": 500
    },
    {
      "user": "anonymous",
      "config": {},
      "settings": {
        "params": {},
        "forms": {}
      },
      "apps": [],
      "jobName": "paragraph_1544639099766_1378440563",
      "id": "20181212-182459_165683314",
      "dateCreated": "2018-12-12 18:24:59.766",
      "status": "READY",
      "progressUpdateIntervalMs": 500
    }
  ],
  "name": "Untitled Note 3",
  "id": "2DXUX3X9A",
  "noteParams": {},
  "noteForms": {},
  "angularObjects": {
    "sh:shared_process": [],
    "spark:shared_process": []
  },
  "config": {
    "isZeppelinNotebookCronEnable": false
  },
  "info": {}
}